JspJiaocheng1TianWanzhuanJspWangzhanKaifajishuCYuyanZhongwenwang/README.md
JspJiaocheng1TianWanzhuanJspWangzhanKaifajishuCYuyanZhongwenwang/__init__.py
JspJiaocheng1TianWanzhuanJspWangzhanKaifajishuCYuyanZhongwenwang/__main__.py
JspJiaocheng1TianWanzhuanJspWangzhanKaifajishuCYuyanZhongwenwang/file.epub
JspJiaocheng1TianWanzhuanJspWangzhanKaifajishuCYuyanZhongwenwang/index.html
JspJiaocheng1TianWanzhuanJspWangzhanKaifajishuCYuyanZhongwenwang/css/__init__.py
JspJiaocheng1TianWanzhuanJspWangzhanKaifajishuCYuyanZhongwenwang/css/annotations.css
JspJiaocheng1TianWanzhuanJspWangzhanKaifajishuCYuyanZhongwenwang/css/main.css
JspJiaocheng1TianWanzhuanJspWangzhanKaifajishuCYuyanZhongwenwang/css/normalize.css
JspJiaocheng1TianWanzhuanJspWangzhanKaifajishuCYuyanZhongwenwang/css/popup.css
JspJiaocheng1TianWanzhuanJspWangzhanKaifajishuCYuyanZhongwenwang/font/__init__.py
JspJiaocheng1TianWanzhuanJspWangzhanKaifajishuCYuyanZhongwenwang/font/fontello.eot
JspJiaocheng1TianWanzhuanJspWangzhanKaifajishuCYuyanZhongwenwang/font/fontello.svg
JspJiaocheng1TianWanzhuanJspWangzhanKaifajishuCYuyanZhongwenwang/font/fontello.ttf
JspJiaocheng1TianWanzhuanJspWangzhanKaifajishuCYuyanZhongwenwang/font/fontello.woff
JspJiaocheng1TianWanzhuanJspWangzhanKaifajishuCYuyanZhongwenwang/img/__init__.py
JspJiaocheng1TianWanzhuanJspWangzhanKaifajishuCYuyanZhongwenwang/img/annotator-glyph-sprite.png
JspJiaocheng1TianWanzhuanJspWangzhanKaifajishuCYuyanZhongwenwang/img/annotator-icon-sprite.png
JspJiaocheng1TianWanzhuanJspWangzhanKaifajishuCYuyanZhongwenwang/img/apple-touch-icon.png
JspJiaocheng1TianWanzhuanJspWangzhanKaifajishuCYuyanZhongwenwang/img/cancelfullscreen.png
JspJiaocheng1TianWanzhuanJspWangzhanKaifajishuCYuyanZhongwenwang/img/close.png
JspJiaocheng1TianWanzhuanJspWangzhanKaifajishuCYuyanZhongwenwang/img/fullscreen.png
JspJiaocheng1TianWanzhuanJspWangzhanKaifajishuCYuyanZhongwenwang/img/loader.gif
JspJiaocheng1TianWanzhuanJspWangzhanKaifajishuCYuyanZhongwenwang/img/menu-icon.png
jsp_jiaocheng_1_tian_wanzhuan_jsp_wangzhan_kaifajishu_c_yuyan_zhongwenwang-2024.3.5.0.dist-info/METADATA
jsp_jiaocheng_1_tian_wanzhuan_jsp_wangzhan_kaifajishu_c_yuyan_zhongwenwang-2024.3.5.0.dist-info/WHEEL
jsp_jiaocheng_1_tian_wanzhuan_jsp_wangzhan_kaifajishu_c_yuyan_zhongwenwang-2024.3.5.0.dist-info/entry_points.txt
jsp_jiaocheng_1_tian_wanzhuan_jsp_wangzhan_kaifajishu_c_yuyan_zhongwenwang-2024.3.5.0.dist-info/top_level.txt
jsp_jiaocheng_1_tian_wanzhuan_jsp_wangzhan_kaifajishu_c_yuyan_zhongwenwang-2024.3.5.0.dist-info/RECORD
